odoo8_addon_logistic_requisition_department-8.0.1.2.0-py2.7-nspkg.pth
odoo_addons/logistic_requisition_department/__openerp__.py
odoo_addons/logistic_requisition_department/__init__.py
odoo_addons/logistic_requisition_department/README.rst
odoo_addons/logistic_requisition_department/view/logistic_requisition_line.xml
odoo_addons/logistic_requisition_department/view/logistic_requisition_source.xml
odoo_addons/logistic_requisition_department/view/logistic_requisition.xml
odoo_addons/logistic_requisition_department/model/logistic_requisition.py
odoo_addons/logistic_requisition_department/model/__init__.py
odoo_addons/logistic_requisition_department/tests/__init__.py
odoo_addons/logistic_requisition_department/tests/test_propagate_department.py
odoo8_addon_logistic_requisition_department-8.0.1.2.0.dist-info/top_level.txt
odoo8_addon_logistic_requisition_department-8.0.1.2.0.dist-info/WHEEL
odoo8_addon_logistic_requisition_department-8.0.1.2.0.dist-info/RECORD
odoo8_addon_logistic_requisition_department-8.0.1.2.0.dist-info/metadata.json
odoo8_addon_logistic_requisition_department-8.0.1.2.0.dist-info/DESCRIPTION.rst
odoo8_addon_logistic_requisition_department-8.0.1.2.0.dist-info/METADATA
odoo8_addon_logistic_requisition_department-8.0.1.2.0.dist-info/namespace_packages.txt
