Metadata-Version: 2.0
Name: odoo8-addon-logistic-requisition-department
Version: 8.0.1.2.0
Summary: Logistic Requisitions with Department Categorization
Home-page: http://camptocamp.com
Author: UNKNOWN
Author-email: UNKNOWN
License: AGPL-3
Platform: UNKNOWN
Requires-Dist: odoo (<9.0a,>=8.0a)
Requires-Dist: odoo8-addon-logistic-requisition
Requires-Dist: odoo8-addon-purchase-requisition-department
Classifier: Programming Language :: Python :: 2.7
Classifier: Framework :: Odoo
Classifier: License :: OSI Approved :: GNU Affero General Public License v3
